fisx/DataDir.py
fisx/FisxCythonTools.py
fisx/__init__.py
fisx/_fisx.cp313-win_amd64.pyd
fisx/fisx_data/BindingEnergies.dat
fisx/fisx_data/EADL97_BindingEnergies.dat
fisx/fisx_data/EADL97_KShellConstants.dat
fisx/fisx_data/EADL97_KShellNonradiativeRates.dat
fisx/fisx_data/EADL97_KShellRadiativeRates.dat
fisx/fisx_data/EADL97_LShellConstants.dat
fisx/fisx_data/EADL97_LShellNonradiativeRates.dat
fisx/fisx_data/EADL97_LShellRadiativeRates.dat
fisx/fisx_data/EADL97_MShellConstants.dat
fisx/fisx_data/EADL97_MShellNonradiativeRates.dat
fisx/fisx_data/EADL97_MShellRadiativeRates.dat
fisx/fisx_data/EPDL97_CrossSections.dat
fisx/fisx_data/KShellConstants.dat
fisx/fisx_data/KShellRates.dat
fisx/fisx_data/LICENSE
fisx/fisx_data/LShellConstants.dat
fisx/fisx_data/LShellRates.dat
fisx/fisx_data/MShellConstants.dat
fisx/fisx_data/MShellRates.dat
fisx/fisx_data/README.rst
fisx/fisx_data/TODO
fisx/fisx_data/XCOM_CrossSections.dat
fisx/fisx_data/changelog.txt
fisx/tests/__init__.py
fisx/tests/testAll.py
fisx/tests/testDataDir.py
fisx/tests/testDetector.py
fisx/tests/testEPDL97.py
fisx/tests/testElements.py
fisx/tests/testSimpleSpecfile.py
fisx/tests/testTransmissionTable.py
fisx/tests/testXRF.py
fisx-1.3.2.dist-info/LICENSE
fisx-1.3.2.dist-info/METADATA
fisx-1.3.2.dist-info/WHEEL
fisx-1.3.2.dist-info/top_level.txt
fisx-1.3.2.dist-info/RECORD
