Metadata-Version: 2.1
Name: fisx
Version: 1.3.2
Summary: Quantitative X-Ray Fluorescence Analysis Support Library
Home-page: https://github.com/vasole/fisx
Download-URL: https://github.com/vasole/fisx/archive/v1.3.2.tar.gz
Author: V. Armando Solé
Author-email: sole@esrf.fr
License: MIT
Classifier: Development Status :: 5 - Production/Stable
Classifier: Programming Language :: C++
Classifier: Programming Language :: Python :: 2
Classifier: Programming Language :: Python :: 3
Classifier: Programming Language :: Cython
Classifier: Environment :: Console
Classifier: Intended Audience :: Developers
Classifier: Intended Audience :: End Users/Desktop
Classifier: Intended Audience :: Science/Research
Classifier: License :: OSI Approved :: MIT License
Classifier: Topic :: Software Development :: Libraries :: Python Modules
Classifier: Operating System :: Microsoft :: Windows
Classifier: Operating System :: Unix
Classifier: Operating System :: MacOS :: MacOS X
Classifier: Operating System :: POSIX
Classifier: Topic :: Scientific/Engineering :: Chemistry
Classifier: Topic :: Scientific/Engineering :: Physics
License-File: LICENSE
Requires-Dist: numpy
